circuit_designer/__init__.py
circuit_designer/circuit_canvas.py
circuit_designer/circuit_editor.py
circuit_designer/config_dialog.py
circuit_designer/gate_palette.py
circuit_designer/gui_main.py
circuit_designer/training_dialog.py
circuit_designer/workflow_bridge.py
circuit_optimization/__init__.py
circuit_optimization/api.py
circuit_optimization/circuit_optimizer.py
circuit_optimization/utils.py
circuit_optimization/strategies/__init__.py
circuit_optimization/strategies/ml_based.py
circuit_optimization/strategies/rl_based.py
circuit_optimization/strategies/rule_based.py
code_switcher/__init__.py
code_switcher/code_switcher.py
configuration_management/__init__.py
configuration_management/config_manager.py
configuration_management/schema_validator.py
evaluation/__init__.py
evaluation/__main__.py
evaluation/evaluation_framework.py
evaluation/test_surface_code_layouts.py
execution_simulation/__init__.py
execution_simulation/execution_simulator.py
fault_tolerant_circuit_builder/__init__.py
fault_tolerant_circuit_builder/ft_circuit_builder.py
hardware_abstraction/__init__.py
hardware_abstraction/device_abstraction.py
hardware_abstraction/hardware_config_loader.py
logging_results/__init__.py
logging_results/logging_results_manager.py
orchestration_controller/__init__.py
orchestration_controller/orchestrator.py
scode/__init__.py
scode/api.py
scode/orchestrator.py
scode/code_switcher/code_switcher.py
scode/graph_transformer/__init__.py
scode/graph_transformer/__main__.py
scode/graph_transformer/graph_transformer.py
scode/heuristic_layer/__init__.py
scode/heuristic_layer/__main__.py
scode/heuristic_layer/config_loader.py
scode/heuristic_layer/heuristic_initialization_layer.py
scode/heuristic_layer/surface_code.py
scode/heuristic_layer/surface_code_object.py
scode/multi_patch_mapper/__init__.py
scode/multi_patch_mapper/__main__.py
scode/multi_patch_mapper/multi_patch_mapper.py
scode/reward_engine/__init__.py
scode/reward_engine/reward_engine.py
scode/rl_agent/__init__.py
quantum_surface_code_generator-0.1.0.dist-info/METADATA
quantum_surface_code_generator-0.1.0.dist-info/WHEEL
quantum_surface_code_generator-0.1.0.dist-info/entry_points.txt
quantum_surface_code_generator-0.1.0.dist-info/top_level.txt
quantum_surface_code_generator-0.1.0.dist-info/RECORD
