Metadata-Version: 2.4
Name: quantum_surface_code_generator
Version: 0.1.0
Summary: Quantum Surface Code Generator using RL with GUI
Author: Your Name
Requires-Dist: PySide6
Requires-Dist: PyYAML
Requires-Dist: jsonschema
Requires-Dist: qiskit
Requires-Dist: networkx
Requires-Dist: matplotlib
Requires-Dist: numpy
Requires-Dist: stable-baselines3
Requires-Dist: scikit-learn
Requires-Dist: pandas
Requires-Dist: torch
Requires-Dist: gymnasium
Requires-Dist: stim
Requires-Dist: pymatching
Dynamic: author
Dynamic: requires-dist
Dynamic: summary
